{
  "date": "2026-06-03",
  "generated_at": "12:38 AM CT",
  "picks": [
    {
      "game": "SD @ PHI",
      "pick": "SD",
      "side": "AWAY",
      "pitcher": "Walker Buehler",
      "opp_pitcher": "Cristopher S\u00e1nchez",
      "odds": 193,
      "best_book": "BetOnline",
      "edge": 0.0603,
      "model_prob": 0.4016,
      "market_prob": 0.3442,
      "fair_odds": "+149",
      "break_even": 0.3413,
      "kelly_units": 1.15,
      "verdict": "\u2705 VALUE",
      "narrative": "Playing on the road, SD's model quality signals outweigh the home-field headwind \u2014 the market over-adjusts for the travel disadvantage.",
      "lineups_confirmed": false,
      "is_preview": true
    },
    {
      "game": "CLE @ NYY",
      "pick": "CLE",
      "side": "AWAY",
      "pitcher": "Gavin Williams",
      "opp_pitcher": "Gerrit Cole",
      "odds": 144,
      "best_book": "ProphetX",
      "edge": 0.056,
      "model_prob": 0.4658,
      "market_prob": 0.41,
      "fair_odds": "+115",
      "break_even": 0.4098,
      "kelly_units": 1.19,
      "verdict": "\u2705 VALUE",
      "narrative": "A multi-factor convergence edge: an even pitching matchup (Gavin Williams 3.70 vs.",
      "lineups_confirmed": false,
      "is_preview": true
    },
    {
      "game": "PIT @ HOU",
      "pick": "HOU",
      "side": "HOME",
      "pitcher": "Spencer Arrighetti",
      "opp_pitcher": "Paul Skenes",
      "odds": 139,
      "best_book": "Novig",
      "edge": 0.0498,
      "model_prob": 0.4682,
      "market_prob": 0.4116,
      "fair_odds": "+114",
      "break_even": 0.4184,
      "kelly_units": 1.07,
      "verdict": "\u2705 VALUE",
      "narrative": "Venue advantage is the model's top signal for HOU: 2026 park data and home-game performance generate a log-odds boost the market's flat moneyline underweights for HOU.",
      "lineups_confirmed": false,
      "is_preview": true
    },
    {
      "game": "SF @ MIL",
      "pick": "SF",
      "side": "AWAY",
      "pitcher": "Logan Webb",
      "opp_pitcher": "TBD",
      "odds": 135,
      "best_book": "BetRivers",
      "edge": 0.0398,
      "model_prob": 0.4653,
      "market_prob": 0.4289,
      "fair_odds": "+115",
      "break_even": 0.4255,
      "kelly_units": 0.86,
      "verdict": "\u2705 VALUE",
      "narrative": "Playing on the road, SF's model quality signals outweigh the home-field headwind \u2014 the market over-adjusts for the travel disadvantage.",
      "lineups_confirmed": false,
      "is_preview": true
    },
    {
      "game": "KC @ CIN",
      "pick": "KC",
      "side": "AWAY",
      "pitcher": "Stephen Kolek",
      "opp_pitcher": "Chase Burns",
      "odds": 140,
      "best_book": "Novig",
      "edge": 0.0311,
      "model_prob": 0.4478,
      "market_prob": 0.4207,
      "fair_odds": "+123",
      "break_even": 0.4167,
      "kelly_units": 0.66,
      "verdict": "\u2705 VALUE",
      "narrative": "Playing on the road, KC's model quality signals outweigh the home-field headwind \u2014 the market over-adjusts for the travel disadvantage.",
      "lineups_confirmed": false,
      "is_preview": true
    },
    {
      "game": "OAK @ CHC",
      "pick": "OAK",
      "side": "AWAY",
      "pitcher": "Jeffrey Springs",
      "opp_pitcher": "Colin Rea",
      "odds": 116,
      "best_book": "Novig",
      "edge": 0.0309,
      "model_prob": 0.4939,
      "market_prob": 0.4589,
      "fair_odds": "+102",
      "break_even": 0.463,
      "kelly_units": 0.72,
      "verdict": "\u2705 VALUE",
      "narrative": "Playing on the road, OAK carries a modest pitching edge (Jeffrey Springs at 4.54 xFIP vs.",
      "lineups_confirmed": false,
      "is_preview": true
    },
    {
      "game": "TOR @ ATL",
      "pick": "TOR",
      "side": "AWAY",
      "pitcher": "Patrick Corbin",
      "opp_pitcher": "Grant Holmes",
      "odds": 135,
      "best_book": "Novig",
      "edge": 0.021,
      "model_prob": 0.4465,
      "market_prob": 0.4225,
      "fair_odds": "+124",
      "break_even": 0.4255,
      "kelly_units": 0.46,
      "verdict": "\ud83d\udfe1 MARGINAL",
      "narrative": "Playing on the road, TOR carries a modest pitching edge (Patrick Corbin at 4.32 xFIP vs.",
      "lineups_confirmed": false,
      "is_preview": true
    }
  ],
  "signal_count": 7,
  "games_in_cache": 15,
  "note": "Opening line preview \u2014 lineups not yet confirmed. Model uses projected lineups with lineup certainty shrinkage applied. Refreshed automatically at 7, 9, and 11 PM CT as more lines post. Verify starting pitchers and lineups before betting."
}