{
  "date": "2026-06-24",
  "generated_at": "8:19 PM CT \u00b7 Jun 24",
  "generated_at_utc": "2026-06-25T01:19:46Z",
  "no_picks_yet": false,
  "picks": [
    {
      "game": "PHI @ WSH",
      "pick": "WSH",
      "side": "HOME",
      "pick_type": "MONEYLINE",
      "meta": "SP: Miles Mikolas",
      "posted_at": "8:06 AM CT",
      "game_time": "2026-06-24T22:45:00Z",
      "temp_f": 70.6,
      "wind_speed_mph": 5.6,
      "wind_dir_degrees": 200.0,
      "is_domed": false,
      "model_prob": 0.5429,
      "market_prob": 0.4537,
      "edge": 0.0924,
      "ev_per_100": 20.52,
      "odds": 122,
      "best_odds": 122,
      "best_book": "Novig",
      "fair_odds": "-119",
      "playable_to": -101,
      "break_even": 0.4505,
      "kelly_units": 2.1,
      "line_open": 116,
      "line_current": 116,
      "odds_history": [
        {
          "t": "2026-06-24T13:06",
          "odds": 122
        },
        {
          "t": "2026-06-24T17:19",
          "odds": 117
        },
        {
          "t": "2026-06-24T18:19",
          "odds": 120
        },
        {
          "t": "2026-06-24T19:19",
          "odds": 111
        },
        {
          "t": "2026-06-24T20:18",
          "odds": 112
        },
        {
          "t": "2026-06-24T21:18",
          "odds": 114
        },
        {
          "t": "2026-06-24T22:18",
          "odds": 115
        }
      ],
      "clv": null,
      "closing_prob": null,
      "sharp_movement": false,
      "steam_move": false,
      "model_total": null,
      "market_total": null,
      "book_odds": {
        "FanDuel": -360,
        "Novig": -292,
        "ESPN Bet": -420,
        "DraftKings": -344,
        "BetMGM": -400,
        "MyBookie": -400,
        "Betway": -350,
        "Hard Rock": -350,
        "ProphetX": -270,
        "Pinnacle": -225,
        "Bovada": -335,
        "BetRivers": -335
      },
      "pitcher": "Miles Mikolas",
      "opp_pitcher": "Aaron Nola",
      "starter_swapped": false,
      "factors": [],
      "raw_stats": {
        "pick_xfip": 4.489,
        "opp_xfip": 4.562,
        "pick_oaa": -8,
        "opp_oaa": -18,
        "pick_bp_pitches": 150,
        "opp_bp_pitches": 150,
        "pick_bp_xfip": 4.35,
        "opp_bp_xfip": 4.35,
        "pick_xera": null,
        "opp_xera": null,
        "pick_xera_pct": null,
        "opp_xera_pct": null,
        "pick_whiff_pct": 1.0,
        "opp_whiff_pct": 48.0,
        "pick_kbb_pct": null,
        "opp_kbb_pct": 0.1562,
        "pick_bvp_shift": 0.0,
        "pick_arsenal_fit": -0.3307,
        "opp_arsenal_fit": -0.2053,
        "pick_lineup_confirmed": false,
        "opp_lineup_confirmed": false,
        "pick_proj_ip": 7.2,
        "opp_proj_ip": 5.1,
        "pick_era": null,
        "opp_era": 5.71,
        "pick_k_pct": null,
        "opp_k_pct": 0.2312,
        "ump_name": "",
        "pick_home_w": 17,
        "pick_home_l": 23,
        "pinnacle_ml_open": 116.0,
        "pick_bullpen_recent_xfip": null,
        "opp_bullpen_recent_xfip": null,
        "opp_starter_hand": "R",
        "pick_ops_vs_hand": null,
        "park_factor": 0.974
      },
      "adj_breakdown": {
        "adjustments": [
          {
            "label": "Defense (OAA)",
            "pp": 0.3,
            "positive": true,
            "group": "team"
          },
          {
            "label": "Home field",
            "pp": 0.27,
            "positive": true,
            "group": "team"
          }
        ],
        "total_adj_pp": 0.57,
        "shrink_note": null,
        "note": "~"
      },
      "narrative": "A multi-factor convergence edge: an even pitching matchup (Miles Mikolas 4.49 vs. Aaron Nola 4.56 xFIP). No single signal dominates \u2014 the probability gap of 8.9pp reflects several independent inputs each pushing in the same direction. The model's fair price is -119 vs. the +122 available. Model prices WSH at 54.3% to win; Pinnacle implies 45.4% (+122) \u2014 a 8.9-point gap. Against this: arsenal matchup: the opposing lineup's handedness profile creates a modest pitch-type headwind for Miles Mikolas \u2014 factored in, but not enough to erase the overall edge. Key risk: Miles Mikolas is projected to work deep (7.2 IP) \u2014 the times-through-order penalty applies from the 3rd cycle onward. If the lineup adjusts late, the starter quality edge compresses.",
      "run_line": {
        "spread": "-1.5",
        "model_prob": 0.4042,
        "fair_odds": "+147",
        "book_odds": null,
        "edge": null
      },
      "total": null,
      "current_edge": null,
      "current_model_prob": null,
      "current_refresh_time": "8:17 PM CT",
      "current_recommendation": null,
      "current_flipped_team": null,
      "current_flipped_edge": null,
      "current_pitcher": null,
      "current_fair_odds": null,
      "current_playable_to": null,
      "current_lineup_confirmed": null,
      "current_opp_lineup_confirmed": null,
      "current_top_factors": [],
      "model_change": null,
      "verdict": "\u2705 STRONG",
      "kelly_multiplier": 1.0,
      "downgrade_reasons": "",
      "is_flagged": false,
      "projected_starter": false
    },
    {
      "game": "NYY @ DET",
      "pick": "NYY",
      "side": "AWAY",
      "pick_type": "MONEYLINE",
      "meta": "SP: Ryan Weathers",
      "posted_at": "8:06 AM CT",
      "game_time": "2026-06-24T22:40:00Z",
      "temp_f": 66.5,
      "wind_speed_mph": 4.4,
      "wind_dir_degrees": 154.0,
      "is_domed": false,
      "model_prob": 0.5019,
      "market_prob": 0.4281,
      "edge": 0.0671,
      "ev_per_100": 15.44,
      "odds": 130,
      "best_odds": 130,
      "best_book": "Novig",
      "fair_odds": "-101",
      "playable_to": 116,
      "break_even": 0.4348,
      "kelly_units": 0.74,
      "line_open": 129,
      "line_current": 129,
      "odds_history": [
        {
          "t": "2026-06-24T13:06",
          "odds": 130
        },
        {
          "t": "2026-06-24T16:17",
          "odds": 122
        },
        {
          "t": "2026-06-24T17:19",
          "odds": 120
        },
        {
          "t": "2026-06-24T18:19",
          "odds": 118
        },
        {
          "t": "2026-06-24T19:19",
          "odds": 117
        },
        {
          "t": "2026-06-24T21:18",
          "odds": 115
        },
        {
          "t": "2026-06-24T22:18",
          "odds": 117
        }
      ],
      "clv": null,
      "closing_prob": null,
      "sharp_movement": false,
      "steam_move": false,
      "model_total": null,
      "market_total": null,
      "book_odds": {
        "FanDuel": -3000,
        "Novig": -1983,
        "ESPN Bet": -4000,
        "DraftKings": -3000,
        "BetMGM": -5000,
        "Betway": -5000,
        "Hard Rock": -2200,
        "ProphetX": -2200,
        "Pinnacle": -1848,
        "Bovada": -2000
      },
      "pitcher": "Ryan Weathers",
      "opp_pitcher": "Tarik Skubal",
      "starter_swapped": false,
      "factors": [
        {
          "label": "Pitcher Quality (xFIP)",
          "value": -0.74
        },
        {
          "label": "Defense (OAA)",
          "value": 0.0178
        }
      ],
      "raw_stats": {
        "pick_xfip": 4.217,
        "opp_xfip": 3.436,
        "pick_oaa": -1,
        "opp_oaa": -16,
        "pick_bp_pitches": 150,
        "opp_bp_pitches": 150,
        "pick_bp_xfip": 4.35,
        "opp_bp_xfip": 4.35,
        "pick_xera": null,
        "opp_xera": null,
        "pick_xera_pct": null,
        "opp_xera_pct": null,
        "pick_whiff_pct": 61.0,
        "opp_whiff_pct": 76.0,
        "pick_kbb_pct": 0.2049,
        "opp_kbb_pct": 0.2311,
        "pick_bvp_shift": 0.0,
        "pick_arsenal_fit": -0.0405,
        "opp_arsenal_fit": 0.1854,
        "pick_lineup_confirmed": false,
        "opp_lineup_confirmed": false,
        "pick_proj_ip": 5.6,
        "opp_proj_ip": 5.6,
        "pick_era": 4.13,
        "opp_era": 3.02,
        "pick_k_pct": 0.2722,
        "opp_k_pct": 0.2689,
        "ump_name": "",
        "pick_home_w": 25,
        "pick_home_l": 16,
        "pinnacle_ml_open": 129.0,
        "pick_bullpen_recent_xfip": null,
        "opp_bullpen_recent_xfip": null,
        "opp_starter_hand": "R",
        "pick_ops_vs_hand": null,
        "park_factor": 1.0
      },
      "adj_breakdown": {
        "adjustments": [
          {
            "label": "Pitcher quality (xFIP)",
            "pp": -0.74,
            "positive": false,
            "group": "pitcher"
          },
          {
            "label": "Defense (OAA)",
            "pp": 0.44,
            "positive": true,
            "group": "team"
          },
          {
            "label": "Home field",
            "pp": -0.2,
            "positive": false,
            "group": "team"
          }
        ],
        "total_adj_pp": -0.5,
        "shrink_note": null,
        "note": "~"
      },
      "narrative": "Tarik Skubal (3.44 xFIP) has a quality edge over Ryan Weathers (4.22), yet the market has over-discounted NYY: model prices NYY at 50.2% to win; Pinnacle implies 42.8% (+130) \u2014 a 7.4-point gap. Supporting this: rest advantage: NYY is the fresher team \u2014 the opponent played yesterday with 150 bullpen pitches in the last 3 days, a fatigue factor moneylines price more slowly than run lines. Key risk: Tarik Skubal (3.44 xFIP) is the sharper starter \u2014 a 0.78-point gap that has to be overcome by NYY's other model signals. This pick requires those signals to hold.",
      "run_line": {
        "spread": "1.5",
        "model_prob": 0.7319,
        "fair_odds": "-273",
        "book_odds": -170,
        "edge": 0.1023
      },
      "total": null,
      "current_edge": null,
      "current_model_prob": null,
      "current_refresh_time": "8:17 PM CT",
      "current_recommendation": null,
      "current_flipped_team": null,
      "current_flipped_edge": null,
      "current_pitcher": null,
      "current_fair_odds": null,
      "current_playable_to": null,
      "current_lineup_confirmed": null,
      "current_opp_lineup_confirmed": null,
      "current_top_factors": [],
      "model_change": null,
      "verdict": "\u2b07\ufe0f REDUCED CONF.",
      "kelly_multiplier": 1.0,
      "downgrade_reasons": "away_worse_sp_fip",
      "is_flagged": true,
      "projected_starter": false
    },
    {
      "game": "KC @ TB",
      "pick": "KC",
      "side": "AWAY",
      "pick_type": "MONEYLINE",
      "meta": "SP: Noah Cameron",
      "posted_at": "8:06 AM CT",
      "game_time": "2026-06-24T22:40:00Z",
      "temp_f": 72.0,
      "wind_speed_mph": 0.0,
      "wind_dir_degrees": 0.0,
      "is_domed": true,
      "model_prob": 0.4849,
      "market_prob": 0.4263,
      "edge": 0.0612,
      "ev_per_100": 14.44,
      "odds": 136,
      "best_odds": 136,
      "best_book": "ProphetX",
      "fair_odds": "+106",
      "playable_to": 125,
      "break_even": 0.4237,
      "kelly_units": 1.33,
      "line_open": 130,
      "line_current": 130,
      "odds_history": [
        {
          "t": "2026-06-24T13:06",
          "odds": 136
        },
        {
          "t": "2026-06-24T14:18",
          "odds": 134
        },
        {
          "t": "2026-06-24T15:17",
          "odds": 135
        },
        {
          "t": "2026-06-24T16:17",
          "odds": 136
        },
        {
          "t": "2026-06-24T19:19",
          "odds": 138
        },
        {
          "t": "2026-06-24T20:18",
          "odds": 135
        },
        {
          "t": "2026-06-24T22:18",
          "odds": 133
        }
      ],
      "clv": null,
      "closing_prob": null,
      "sharp_movement": false,
      "steam_move": false,
      "model_total": null,
      "market_total": null,
      "book_odds": {
        "FanDuel": 2500,
        "Novig": 1567,
        "ESPN Bet": 2000,
        "BetMGM": 3000,
        "Betway": 1400
      },
      "pitcher": "Noah Cameron",
      "opp_pitcher": "Griffin Jax",
      "starter_swapped": false,
      "factors": [
        {
          "label": "Pitcher Quality (xFIP)",
          "value": 0.22
        },
        {
          "label": "Home Field",
          "value": -0.045
        },
        {
          "label": "Defense (OAA)",
          "value": 0.025
        }
      ],
      "raw_stats": {
        "pick_xfip": 4.019,
        "opp_xfip": 4.248,
        "pick_oaa": 10,
        "opp_oaa": -13,
        "pick_bp_pitches": 150,
        "opp_bp_pitches": 150,
        "pick_bp_xfip": 4.35,
        "opp_bp_xfip": 4.35,
        "pick_xera": null,
        "opp_xera": null,
        "pick_xera_pct": null,
        "opp_xera_pct": null,
        "pick_whiff_pct": 44.0,
        "opp_whiff_pct": 87.0,
        "pick_kbb_pct": 0.1584,
        "opp_kbb_pct": null,
        "pick_bvp_shift": 0.0,
        "pick_arsenal_fit": -0.111,
        "opp_arsenal_fit": -0.3573,
        "pick_lineup_confirmed": false,
        "opp_lineup_confirmed": false,
        "pick_proj_ip": 5.3,
        "opp_proj_ip": 5.1,
        "pick_era": 4.2,
        "opp_era": null,
        "pick_k_pct": 0.2174,
        "opp_k_pct": null,
        "ump_name": "",
        "pick_home_w": 15,
        "pick_home_l": 24,
        "pinnacle_ml_open": 130.0,
        "pick_bullpen_recent_xfip": null,
        "opp_bullpen_recent_xfip": null,
        "opp_starter_hand": "R",
        "pick_ops_vs_hand": null,
        "park_factor": 0.958
      },
      "adj_breakdown": {
        "adjustments": [
          {
            "label": "Home field",
            "pp": -1.12,
            "positive": false,
            "group": "team"
          },
          {
            "label": "Defense (OAA)",
            "pp": 0.62,
            "positive": true,
            "group": "team"
          },
          {
            "label": "Pitcher quality (xFIP)",
            "pp": 0.22,
            "positive": true,
            "group": "pitcher"
          },
          {
            "label": "Starter rest",
            "pp": -0.17,
            "positive": false,
            "group": "schedule"
          }
        ],
        "total_adj_pp": -0.45,
        "shrink_note": null,
        "note": "~"
      },
      "narrative": "Starter quality differential drives this pick: Noah Cameron (4.02 xFIP) has a measurable edge over Griffin Jax (4.25 xFIP) \u2014 model prices KC at 48.5% to win; Pinnacle implies 42.6% (+136) \u2014 a 5.9-point gap. Supporting this: rest advantage: KC is the fresher team \u2014 the opponent played yesterday with 150 bullpen pitches in the last 3 days, a fatigue factor moneylines price more slowly than run lines. Model inputs solid, no critical gaps.",
      "run_line": {
        "spread": "1.5",
        "model_prob": 0.7103,
        "fair_odds": "-245",
        "book_odds": -160,
        "edge": 0.0949
      },
      "total": null,
      "current_edge": null,
      "current_model_prob": null,
      "current_refresh_time": "8:17 PM CT",
      "current_recommendation": null,
      "current_flipped_team": null,
      "current_flipped_edge": null,
      "current_pitcher": null,
      "current_fair_odds": null,
      "current_playable_to": null,
      "current_lineup_confirmed": null,
      "current_opp_lineup_confirmed": null,
      "current_top_factors": [],
      "model_change": null,
      "verdict": "\u2705 VALUE",
      "kelly_multiplier": 1.0,
      "downgrade_reasons": "",
      "is_flagged": false,
      "projected_starter": false
    },
    {
      "game": "SEA @ PIT",
      "pick": "PIT",
      "side": "HOME",
      "pick_type": "MONEYLINE",
      "meta": "SP: Braxton Ashcraft",
      "posted_at": "8:06 AM CT",
      "game_time": "2026-06-24T22:40:00Z",
      "temp_f": 67.3,
      "wind_speed_mph": 5.6,
      "wind_dir_degrees": 188.0,
      "is_domed": false,
      "model_prob": 0.5823,
      "market_prob": 0.5152,
      "edge": 0.0608,
      "ev_per_100": 11.65,
      "odds": -109,
      "best_odds": -109,
      "best_book": "ProphetX",
      "fair_odds": "-139",
      "playable_to": -118,
      "break_even": 0.5215,
      "kelly_units": 1.59,
      "line_open": -111,
      "line_current": -111,
      "odds_history": [
        {
          "t": "2026-06-24T13:06",
          "odds": -109
        },
        {
          "t": "2026-06-24T15:17",
          "odds": -106
        },
        {
          "t": "2026-06-24T16:17",
          "odds": -110
        },
        {
          "t": "2026-06-24T17:19",
          "odds": -108
        },
        {
          "t": "2026-06-24T18:19",
          "odds": -111
        },
        {
          "t": "2026-06-24T20:18",
          "odds": -107
        },
        {
          "t": "2026-06-24T21:18",
          "odds": -104
        },
        {
          "t": "2026-06-24T22:18",
          "odds": -106
        }
      ],
      "clv": null,
      "closing_prob": null,
      "sharp_movement": false,
      "steam_move": false,
      "model_total": null,
      "market_total": null,
      "book_odds": {
        "Novig": -100000,
        "BetMGM": -10000,
        "Betway": -10000
      },
      "pitcher": "Braxton Ashcraft",
      "opp_pitcher": "Bryan Woo",
      "starter_swapped": false,
      "factors": [
        {
          "label": "Pitcher Quality (xFIP)",
          "value": 0.33
        },
        {
          "label": "Defense (OAA)",
          "value": 0.0166
        }
      ],
      "raw_stats": {
        "pick_xfip": 3.247,
        "opp_xfip": 3.607,
        "pick_oaa": -11,
        "opp_oaa": -25,
        "pick_bp_pitches": 150,
        "opp_bp_pitches": 150,
        "pick_bp_xfip": 4.35,
        "opp_bp_xfip": 4.35,
        "pick_xera": null,
        "opp_xera": null,
        "pick_xera_pct": null,
        "opp_xera_pct": null,
        "pick_whiff_pct": 63.0,
        "opp_whiff_pct": 44.0,
        "pick_kbb_pct": 0.2033,
        "opp_kbb_pct": 0.2034,
        "pick_bvp_shift": 0.0,
        "pick_arsenal_fit": 0.7043,
        "opp_arsenal_fit": 0.3872,
        "pick_lineup_confirmed": false,
        "opp_lineup_confirmed": false,
        "pick_proj_ip": 5.7,
        "opp_proj_ip": 5.7,
        "pick_era": 3.18,
        "opp_era": 3.94,
        "pick_k_pct": 0.2629,
        "opp_k_pct": 0.2486,
        "ump_name": "",
        "pick_home_w": 20,
        "pick_home_l": 20,
        "pinnacle_ml_open": -111.0,
        "pick_bullpen_recent_xfip": null,
        "opp_bullpen_recent_xfip": null,
        "opp_starter_hand": "R",
        "pick_ops_vs_hand": null,
        "park_factor": 0.978
      },
      "adj_breakdown": {
        "adjustments": [
          {
            "label": "Defense (OAA)",
            "pp": 0.4,
            "positive": true,
            "group": "team"
          },
          {
            "label": "Pitcher quality (xFIP)",
            "pp": 0.33,
            "positive": true,
            "group": "pitcher"
          },
          {
            "label": "Home field",
            "pp": 0.32,
            "positive": true,
            "group": "team"
          }
        ],
        "total_adj_pp": 1.05,
        "shrink_note": null,
        "note": "~"
      },
      "narrative": "The market is mispricing a clear starter advantage: Braxton Ashcraft (3.25 xFIP, with a 20.3% K-BB% (elite command)) has a measurable edge over Bryan Woo (3.61 xFIP) \u2014 model prices PIT at 58.2% to win; Pinnacle implies 51.5% (-109) \u2014 a 6.7-point gap. Supporting this: arsenal matchup: Braxton Ashcraft's breaking-ball-heavy arsenal maps favorably against the opposing lineup's RHH-heavy profile today \u2014 a contact-quality signal xFIP doesn't fully capture. Model inputs solid, no critical gaps.",
      "run_line": {
        "spread": "-1.5",
        "model_prob": 0.4354,
        "fair_odds": "+130",
        "book_odds": 188,
        "edge": 0.0882
      },
      "total": null,
      "current_edge": null,
      "current_model_prob": null,
      "current_refresh_time": "8:17 PM CT",
      "current_recommendation": null,
      "current_flipped_team": null,
      "current_flipped_edge": null,
      "current_pitcher": null,
      "current_fair_odds": null,
      "current_playable_to": null,
      "current_lineup_confirmed": null,
      "current_opp_lineup_confirmed": null,
      "current_top_factors": [],
      "model_change": null,
      "verdict": "\u2705 VALUE",
      "kelly_multiplier": 1.0,
      "downgrade_reasons": "",
      "is_flagged": false,
      "projected_starter": false
    },
    {
      "game": "LAD @ MIN",
      "pick": "MIN",
      "side": "HOME",
      "pick_type": "MONEYLINE",
      "meta": "SP: Joe Ryan",
      "posted_at": "8:06 AM CT",
      "game_time": "2026-06-24T23:40:00Z",
      "temp_f": 72.0,
      "wind_speed_mph": 0.0,
      "wind_dir_degrees": 0.0,
      "is_domed": true,
      "model_prob": 0.4361,
      "market_prob": 0.3809,
      "edge": 0.0485,
      "ev_per_100": 12.51,
      "odds": 158,
      "best_odds": 158,
      "best_book": "ProphetX",
      "fair_odds": "+129",
      "playable_to": 152,
      "break_even": 0.3876,
      "kelly_units": 0.99,
      "line_open": 157,
      "line_current": 157,
      "odds_history": [
        {
          "t": "2026-06-24T13:06",
          "odds": 158
        },
        {
          "t": "2026-06-24T17:19",
          "odds": 156
        },
        {
          "t": "2026-06-24T18:19",
          "odds": 155
        },
        {
          "t": "2026-06-24T19:19",
          "odds": 156
        },
        {
          "t": "2026-06-24T20:18",
          "odds": 152
        },
        {
          "t": "2026-06-24T21:18",
          "odds": 147
        },
        {
          "t": "2026-06-24T23:18",
          "odds": 147
        }
      ],
      "clv": null,
      "closing_prob": null,
      "sharp_movement": false,
      "steam_move": false,
      "model_total": null,
      "market_total": null,
      "book_odds": {
        "FanDuel": 340,
        "Novig": 335,
        "MyBookie": 235,
        "Betway": 300,
        "Hard Rock": 260,
        "BetRivers": 300,
        "ProphetX": 365,
        "DraftKings": 287,
        "BetMGM": 300,
        "Pinnacle": 242,
        "Bovada": 315,
        "ESPN Bet": 300
      },
      "pitcher": "Joe Ryan",
      "opp_pitcher": "Shohei Ohtani",
      "starter_swapped": false,
      "factors": [
        {
          "label": "Pitcher Quality (xFIP)",
          "value": -0.13
        },
        {
          "label": "Defense (OAA)",
          "value": -0.025
        }
      ],
      "raw_stats": {
        "pick_xfip": 3.313,
        "opp_xfip": 3.173,
        "pick_oaa": -15,
        "opp_oaa": 23,
        "pick_bp_pitches": 150,
        "opp_bp_pitches": 150,
        "pick_bp_xfip": 4.35,
        "opp_bp_xfip": 4.35,
        "pick_xera": null,
        "opp_xera": null,
        "pick_xera_pct": null,
        "opp_xera_pct": null,
        "pick_whiff_pct": 52.0,
        "opp_whiff_pct": 82.0,
        "pick_kbb_pct": 0.2301,
        "opp_kbb_pct": 0.1938,
        "pick_bvp_shift": 0.0,
        "pick_arsenal_fit": 0.6477,
        "opp_arsenal_fit": 1.0,
        "pick_lineup_confirmed": false,
        "opp_lineup_confirmed": false,
        "pick_proj_ip": 5.4,
        "opp_proj_ip": 5.8,
        "pick_era": 2.99,
        "opp_era": 1.47,
        "pick_k_pct": 0.2812,
        "opp_k_pct": 0.2699,
        "ump_name": "",
        "pick_home_w": 20,
        "pick_home_l": 21,
        "pinnacle_ml_open": 157.0,
        "pick_bullpen_recent_xfip": null,
        "opp_bullpen_recent_xfip": null,
        "opp_starter_hand": "R",
        "pick_ops_vs_hand": null,
        "park_factor": 1.006
      },
      "adj_breakdown": {
        "adjustments": [
          {
            "label": "Defense (OAA)",
            "pp": -0.61,
            "positive": false,
            "group": "team"
          },
          {
            "label": "Home field",
            "pp": 0.2,
            "positive": true,
            "group": "team"
          }
        ],
        "total_adj_pp": -0.41,
        "shrink_note": null,
        "note": "~"
      },
      "narrative": "Shohei Ohtani (3.17 xFIP) has a quality edge over Joe Ryan (3.31), yet the market has over-discounted MIN: model prices MIN at 43.6% to win; Pinnacle implies 38.1% (+158) \u2014 a 5.5-point gap. Supporting this: arsenal matchup: Joe Ryan's breaking-ball-heavy arsenal maps favorably against the opposing lineup's RHH-heavy profile today \u2014 a contact-quality signal xFIP doesn't fully capture.",
      "run_line": {
        "spread": "-1.5",
        "model_prob": 0.2517,
        "fair_odds": "+297",
        "book_odds": null,
        "edge": null
      },
      "total": null,
      "current_edge": null,
      "current_model_prob": null,
      "current_refresh_time": "8:17 PM CT",
      "current_recommendation": null,
      "current_flipped_team": null,
      "current_flipped_edge": null,
      "current_pitcher": null,
      "current_fair_odds": null,
      "current_playable_to": null,
      "current_lineup_confirmed": null,
      "current_opp_lineup_confirmed": null,
      "current_top_factors": [],
      "model_change": null,
      "verdict": "\ud83d\udfe1 CONDITIONAL",
      "kelly_multiplier": 1.0,
      "downgrade_reasons": "",
      "is_flagged": false,
      "projected_starter": false
    },
    {
      "game": "BOS @ COL",
      "pick": "COL",
      "side": "HOME",
      "pick_type": "MONEYLINE",
      "meta": "SP: Kyle Freeland",
      "posted_at": "8:06 AM CT",
      "game_time": "2026-06-24T19:10:00Z",
      "temp_f": 82.7,
      "wind_speed_mph": 6.0,
      "wind_dir_degrees": 9.0,
      "is_domed": false,
      "model_prob": 0.4466,
      "market_prob": 0.3984,
      "edge": 0.0466,
      "ev_per_100": 11.65,
      "odds": 150,
      "best_odds": 150,
      "best_book": "ProphetX",
      "fair_odds": "+124",
      "playable_to": 146,
      "break_even": 0.4,
      "kelly_units": 0.97,
      "line_open": 146,
      "line_current": 146,
      "odds_history": [
        {
          "t": "2026-06-24T13:06",
          "odds": 150
        },
        {
          "t": "2026-06-24T14:18",
          "odds": 153
        },
        {
          "t": "2026-06-24T15:17",
          "odds": 150
        },
        {
          "t": "2026-06-24T16:17",
          "odds": 153
        },
        {
          "t": "2026-06-24T17:19",
          "odds": 160
        },
        {
          "t": "2026-06-24T18:19",
          "odds": 155
        }
      ],
      "clv": null,
      "closing_prob": null,
      "sharp_movement": false,
      "steam_move": false,
      "model_total": null,
      "market_total": null,
      "book_odds": {},
      "pitcher": "Kyle Freeland",
      "opp_pitcher": "Ranger Suarez",
      "starter_swapped": false,
      "factors": [
        {
          "label": "Pitcher Quality (xFIP)",
          "value": -1.05
        },
        {
          "label": "Home Field",
          "value": 0.045
        },
        {
          "label": "Defense (OAA)",
          "value": -0.025
        }
      ],
      "raw_stats": {
        "pick_xfip": 4.418,
        "opp_xfip": 3.305,
        "pick_oaa": -1,
        "opp_oaa": 21,
        "pick_bp_pitches": 150,
        "opp_bp_pitches": 150,
        "pick_bp_xfip": 4.35,
        "opp_bp_xfip": 4.35,
        "pick_xera": null,
        "opp_xera": null,
        "pick_xera_pct": null,
        "opp_xera_pct": null,
        "pick_whiff_pct": 26.0,
        "opp_whiff_pct": 40.0,
        "pick_kbb_pct": 0.1344,
        "opp_kbb_pct": 0.1645,
        "pick_bvp_shift": 0.0,
        "pick_arsenal_fit": -0.7826,
        "opp_arsenal_fit": 0.3995,
        "pick_lineup_confirmed": false,
        "opp_lineup_confirmed": false,
        "pick_proj_ip": 5.2,
        "opp_proj_ip": 5.4,
        "pick_era": 7.36,
        "opp_era": 2.93,
        "pick_k_pct": 0.1869,
        "opp_k_pct": 0.2419,
        "ump_name": "",
        "pick_home_w": 17,
        "pick_home_l": 22,
        "pinnacle_ml_open": 146.0,
        "pick_bullpen_recent_xfip": null,
        "opp_bullpen_recent_xfip": null,
        "opp_starter_hand": "R",
        "pick_ops_vs_hand": null,
        "park_factor": 1.14
      },
      "adj_breakdown": {
        "adjustments": [
          {
            "label": "Home field",
            "pp": 1.11,
            "positive": true,
            "group": "team"
          },
          {
            "label": "Pitcher quality (xFIP)",
            "pp": -1.05,
            "positive": false,
            "group": "pitcher"
          },
          {
            "label": "Defense (OAA)",
            "pp": -0.62,
            "positive": false,
            "group": "team"
          },
          {
            "label": "Day/night",
            "pp": -0.37,
            "positive": false,
            "group": "schedule"
          }
        ],
        "total_adj_pp": -0.93,
        "shrink_note": null,
        "note": "~"
      },
      "narrative": "Ranger Suarez (3.31 xFIP) has a quality edge over Kyle Freeland (4.42), yet the market has over-discounted COL: model prices COL at 44.7% to win; Pinnacle implies 39.8% (+150) \u2014 a 4.8-point gap. One caution: arsenal matchup: the opposing lineup's handedness profile creates a modest pitch-type headwind for Kyle Freeland \u2014 factored in, but not enough to erase the overall edge. Key risk: Ranger Suarez (3.31 xFIP) is the sharper starter \u2014 a 1.11-point gap that has to be overcome by COL's other model signals. This pick requires those signals to hold.",
      "run_line": {
        "spread": "-1.5",
        "model_prob": 0.2646,
        "fair_odds": "+278",
        "book_odds": null,
        "edge": null
      },
      "total": null,
      "current_edge": null,
      "current_model_prob": null,
      "current_refresh_time": "8:17 PM CT",
      "current_recommendation": null,
      "current_flipped_team": null,
      "current_flipped_edge": null,
      "current_pitcher": null,
      "current_fair_odds": null,
      "current_playable_to": null,
      "current_lineup_confirmed": null,
      "current_opp_lineup_confirmed": null,
      "current_top_factors": [],
      "model_change": null,
      "verdict": "\ud83d\udfe1 CONDITIONAL",
      "kelly_multiplier": 1.0,
      "downgrade_reasons": "",
      "is_flagged": false,
      "projected_starter": false
    },
    {
      "game": "MIL @ CIN",
      "pick": "MIL",
      "side": "AWAY",
      "pick_type": "MONEYLINE",
      "meta": "SP: Shane Drohan",
      "posted_at": "8:06 AM CT",
      "game_time": "2026-06-24T23:10:00Z",
      "temp_f": 69.6,
      "wind_speed_mph": 2.4,
      "wind_dir_degrees": 248.0,
      "is_domed": false,
      "model_prob": 0.6165,
      "market_prob": 0.5693,
      "edge": 0.0457,
      "ev_per_100": 8.0,
      "odds": -133,
      "best_odds": -133,
      "best_book": "Novig",
      "fair_odds": "-161",
      "playable_to": -136,
      "break_even": 0.5708,
      "kelly_units": 1.33,
      "line_open": -138,
      "line_current": -138,
      "odds_history": [
        {
          "t": "2026-06-24T13:06",
          "odds": -133
        },
        {
          "t": "2026-06-24T14:18",
          "odds": -132
        },
        {
          "t": "2026-06-24T15:17",
          "odds": -125
        },
        {
          "t": "2026-06-24T18:19",
          "odds": -126
        },
        {
          "t": "2026-06-24T19:19",
          "odds": -125
        },
        {
          "t": "2026-06-24T22:18",
          "odds": -124
        }
      ],
      "clv": null,
      "closing_prob": null,
      "sharp_movement": false,
      "steam_move": false,
      "model_total": null,
      "market_total": null,
      "book_odds": {
        "FanDuel": -1000,
        "Novig": -809,
        "ESPN Bet": -1400,
        "DraftKings": -890,
        "BetMGM": -1200,
        "MyBookie": -1250,
        "Betway": -1099,
        "Hard Rock": -900,
        "ProphetX": -990,
        "Pinnacle": -1537,
        "Bovada": -1100,
        "BetRivers": -1000
      },
      "pitcher": "Shane Drohan",
      "opp_pitcher": "Rhett Lowder",
      "starter_swapped": false,
      "factors": [
        {
          "label": "Pitcher Quality (xFIP)",
          "value": 1.29
        },
        {
          "label": "Home Field",
          "value": -0.02
        }
      ],
      "raw_stats": {
        "pick_xfip": 3.9,
        "opp_xfip": 5.341,
        "pick_oaa": -6,
        "opp_oaa": 1,
        "pick_bp_pitches": 150,
        "opp_bp_pitches": 150,
        "pick_bp_xfip": 4.35,
        "opp_bp_xfip": 4.35,
        "pick_xera": null,
        "opp_xera": null,
        "pick_xera_pct": null,
        "opp_xera_pct": null,
        "pick_whiff_pct": 75.0,
        "opp_whiff_pct": 14.0,
        "pick_kbb_pct": null,
        "opp_kbb_pct": 0.0603,
        "pick_bvp_shift": 0.0,
        "pick_arsenal_fit": 0.5446,
        "opp_arsenal_fit": -0.5342,
        "pick_lineup_confirmed": false,
        "opp_lineup_confirmed": false,
        "pick_proj_ip": 6.7,
        "opp_proj_ip": 5.0,
        "pick_era": null,
        "opp_era": 4.82,
        "pick_k_pct": null,
        "opp_k_pct": 0.181,
        "ump_name": "",
        "pick_home_w": 23,
        "pick_home_l": 14,
        "pinnacle_ml_open": -138.0,
        "pick_bullpen_recent_xfip": null,
        "opp_bullpen_recent_xfip": null,
        "opp_starter_hand": "R",
        "pick_ops_vs_hand": null,
        "park_factor": 1.068
      },
      "adj_breakdown": {
        "adjustments": [
          {
            "label": "Pitcher quality (xFIP)",
            "pp": 1.29,
            "positive": true,
            "group": "pitcher"
          },
          {
            "label": "Home field",
            "pp": -0.47,
            "positive": false,
            "group": "team"
          },
          {
            "label": "Defense (OAA)",
            "pp": -0.19,
            "positive": false,
            "group": "team"
          }
        ],
        "total_adj_pp": 0.63,
        "shrink_note": null,
        "note": "~"
      },
      "narrative": "The market is mispricing a significant starter advantage: Shane Drohan (3.90 xFIP, with a 12.4% swinging-strike rate (above-average)) has a measurable edge over Rhett Lowder (5.34 xFIP, 4.82 ERA \u2014 outperforming their process stats) \u2014 model prices MIL at 61.7% to win; Pinnacle implies 56.9% (-133) \u2014 a 4.7-point gap. Supporting this: arsenal matchup: Shane Drohan's breaking-ball-heavy arsenal maps favorably against the opposing lineup's RHH-heavy profile today \u2014 a contact-quality signal xFIP doesn't fully capture.",
      "run_line": {
        "spread": "1.5",
        "model_prob": 0.8357,
        "fair_odds": "-509",
        "book_odds": null,
        "edge": null
      },
      "total": null,
      "current_edge": null,
      "current_model_prob": null,
      "current_refresh_time": "8:17 PM CT",
      "current_recommendation": null,
      "current_flipped_team": null,
      "current_flipped_edge": null,
      "current_pitcher": null,
      "current_fair_odds": null,
      "current_playable_to": null,
      "current_lineup_confirmed": null,
      "current_opp_lineup_confirmed": null,
      "current_top_factors": [],
      "model_change": null,
      "verdict": "\ud83d\udfe1 CONDITIONAL",
      "kelly_multiplier": 1.0,
      "downgrade_reasons": "",
      "is_flagged": false,
      "projected_starter": false
    },
    {
      "game": "CHC @ MET",
      "pick": "CHC",
      "side": "AWAY",
      "pick_type": "MONEYLINE",
      "meta": "SP: Shota Imanaga",
      "posted_at": "5:18 PM CT",
      "game_time": "2026-06-24T23:10:00Z",
      "temp_f": 72.0,
      "wind_speed_mph": 5.0,
      "wind_dir_degrees": 180.0,
      "is_domed": false,
      "model_prob": 0.5575,
      "market_prob": 0.5071,
      "edge": 0.0453,
      "ev_per_100": 8.85,
      "odds": -105,
      "best_odds": -105,
      "best_book": "ProphetX",
      "fair_odds": "-126",
      "playable_to": -107,
      "break_even": 0.5122,
      "kelly_units": 1.16,
      "line_open": -107,
      "line_current": -107,
      "odds_history": [
        {
          "t": "2026-06-24T13:06",
          "odds": -120
        },
        {
          "t": "2026-06-24T14:18",
          "odds": -112
        },
        {
          "t": "2026-06-24T15:17",
          "odds": 100
        },
        {
          "t": "2026-06-24T22:18",
          "odds": -105
        }
      ],
      "clv": null,
      "closing_prob": null,
      "sharp_movement": false,
      "steam_move": false,
      "model_total": null,
      "market_total": null,
      "book_odds": {
        "FanDuel": -650,
        "Novig": -506,
        "DraftKings": -564,
        "BetMGM": -600,
        "ESPN Bet": -700,
        "BetRivers": -670,
        "ProphetX": -540,
        "Betway": -500,
        "MyBookie": -500,
        "Bovada": -650,
        "Pinnacle": -507,
        "Hard Rock": -500
      },
      "pitcher": "Shota Imanaga",
      "opp_pitcher": "Sean Manaea",
      "starter_swapped": false,
      "factors": [
        {
          "label": "Pitcher Quality (xFIP)",
          "value": -0.28
        },
        {
          "label": "Home Field",
          "value": -0.026
        },
        {
          "label": "Defense (OAA)",
          "value": 0.025
        },
        {
          "label": "Starter Rest",
          "value": -0.015
        }
      ],
      "raw_stats": {
        "pick_xfip": 4.261,
        "opp_xfip": 3.958,
        "pick_oaa": 37,
        "opp_oaa": -8,
        "pick_bp_pitches": 150,
        "opp_bp_pitches": 150,
        "pick_bp_xfip": 4.35,
        "opp_bp_xfip": 4.35,
        "pick_xera": null,
        "opp_xera": null,
        "pick_xera_pct": null,
        "opp_xera_pct": null,
        "pick_whiff_pct": 86.0,
        "opp_whiff_pct": 41.0,
        "pick_kbb_pct": 0.1777,
        "opp_kbb_pct": null,
        "pick_bvp_shift": 0.0,
        "pick_arsenal_fit": 0.2252,
        "opp_arsenal_fit": 0.0794,
        "pick_lineup_confirmed": true,
        "opp_lineup_confirmed": true,
        "pick_proj_ip": 5.6,
        "opp_proj_ip": 5.3,
        "pick_era": 4.26,
        "opp_era": null,
        "pick_k_pct": 0.2407,
        "opp_k_pct": null,
        "ump_name": "Stu Scheurwater",
        "pick_home_w": 19,
        "pick_home_l": 20,
        "pinnacle_ml_open": -107.0,
        "pick_bullpen_recent_xfip": null,
        "opp_bullpen_recent_xfip": null,
        "opp_starter_hand": "R",
        "pick_ops_vs_hand": null,
        "park_factor": 0.968
      },
      "adj_breakdown": {
        "adjustments": [
          {
            "label": "Lineup quality",
            "pp": 0.71,
            "positive": true,
            "group": "lineup"
          },
          {
            "label": "Home field",
            "pp": -0.64,
            "positive": false,
            "group": "team"
          },
          {
            "label": "Defense (OAA)",
            "pp": 0.62,
            "positive": true,
            "group": "team"
          },
          {
            "label": "Starter rest",
            "pp": -0.37,
            "positive": false,
            "group": "schedule"
          },
          {
            "label": "Pitcher quality (xFIP)",
            "pp": -0.28,
            "positive": false,
            "group": "pitcher"
          }
        ],
        "total_adj_pp": 0.04,
        "shrink_note": null,
        "note": "~"
      },
      "narrative": "Sean Manaea (3.96 xFIP) has a quality edge over Shota Imanaga (4.26), yet the market has over-discounted CHC: model prices CHC at 55.8% to win; Pinnacle implies 50.7% (-105) \u2014 a 5.0-point gap. Supporting this: arsenal matchup: Shota Imanaga's pitch mix maps favorably against the opposing lineup's RHH-heavy profile today \u2014 a contact-quality signal xFIP doesn't fully capture.",
      "run_line": {
        "spread": "1.5",
        "model_prob": 0.7806,
        "fair_odds": "-356",
        "book_odds": null,
        "edge": null
      },
      "total": null,
      "current_edge": null,
      "current_model_prob": null,
      "current_refresh_time": "8:17 PM CT",
      "current_recommendation": null,
      "current_flipped_team": null,
      "current_flipped_edge": null,
      "current_pitcher": null,
      "current_fair_odds": null,
      "current_playable_to": null,
      "current_lineup_confirmed": null,
      "current_opp_lineup_confirmed": null,
      "current_top_factors": [],
      "model_change": null,
      "verdict": "\ud83d\udfe1 CONDITIONAL",
      "kelly_multiplier": 1.0,
      "downgrade_reasons": "",
      "is_flagged": false,
      "projected_starter": false
    }
  ],
  "signal_count": 8,
  "posted_count": 8,
  "games_today": 1,
  "yesterday_picks": [
    {
      "game": "HOU @ TOR",
      "pick": "HOU",
      "pitcher": "Peter Lambert",
      "odds": 120,
      "edge": 0.0503,
      "result": "W",
      "clv": 0.0148,
      "pnl_u": 1.2
    },
    {
      "game": "KC @ TB",
      "pick": "KC",
      "pitcher": "Luinder Avila",
      "odds": 170,
      "edge": 0.0593,
      "result": "W",
      "clv": 0.0026,
      "pnl_u": 1.7
    },
    {
      "game": "PHI @ WSH",
      "pick": "WSH",
      "pitcher": "Zack Littell",
      "odds": 156,
      "edge": 0.0801,
      "result": "L",
      "clv": -0.0169,
      "pnl_u": -1.0
    },
    {
      "game": "CHC @ MET",
      "pick": "CHC",
      "pitcher": "Edward Cabrera",
      "odds": 104,
      "edge": 0.0528,
      "result": "W",
      "clv": 0.0281,
      "pnl_u": 1.04
    },
    {
      "game": "MIL @ CIN",
      "pick": "MIL",
      "pitcher": "Brandon Sproat",
      "odds": -101,
      "edge": 0.0735,
      "result": "W",
      "clv": -0.0023,
      "pnl_u": 0.99
    },
    {
      "game": "LAD @ MIN",
      "pick": "MIN",
      "pitcher": "Kendry Rojas",
      "odds": 160,
      "edge": 0.0631,
      "result": "L",
      "clv": -0.0048,
      "pnl_u": -1.0
    },
    {
      "game": "CLE @ CHW",
      "pick": "CHW",
      "pitcher": "Sean Burke",
      "odds": 106,
      "edge": 0.0472,
      "result": "W",
      "clv": 0.0058,
      "pnl_u": 1.06
    },
    {
      "game": "ARI @ STL",
      "pick": "STL",
      "pitcher": "Kyle Leahy",
      "odds": -104,
      "edge": 0.0689,
      "result": "L",
      "clv": -0.0141,
      "pnl_u": -1.0
    },
    {
      "game": "BOS @ COL",
      "pick": "COL",
      "pitcher": "Sean Sullivan",
      "odds": 150,
      "edge": 0.0974,
      "result": "L",
      "clv": 0.0116,
      "pnl_u": -1.0
    },
    {
      "game": "BAL @ LAA",
      "pick": "LAA",
      "pitcher": "Ryan Johnson",
      "odds": 130,
      "edge": 0.0455,
      "result": "W",
      "clv": 0.0019,
      "pnl_u": 1.3
    },
    {
      "game": "TEX @ MIA",
      "pick": "TEX",
      "pitcher": "Cal Quantrill",
      "odds": 150,
      "edge": 0.0421,
      "result": "L",
      "clv": 0.0102,
      "pnl_u": -1.0
    },
    {
      "game": "SEA @ PIT",
      "pick": "PIT",
      "pitcher": "Mitch Keller",
      "odds": 121,
      "edge": 0.0441,
      "result": "L",
      "clv": -0.004,
      "pnl_u": -1.0
    }
  ],
  "correlated_warning": null,
  "season": {
    "wins": 289,
    "losses": 253,
    "units": 77.98,
    "bets": 542,
    "roi": 0.1439
  },
  "last7": {
    "wins": 31,
    "losses": 29,
    "units": 6.33,
    "roi": 0.1055,
    "bets": 60
  },
  "week_picks": [
    {
      "date": "2026-06-17",
      "pick": "BOS",
      "game": "TOR @ BOS",
      "odds": -118,
      "edge": 0.07,
      "result": "L",
      "pnl_u": -1.0
    },
    {
      "date": "2026-06-17",
      "pick": "COL",
      "game": "COL @ CHC",
      "odds": 172,
      "edge": 0.064,
      "result": "L",
      "pnl_u": -1.0
    },
    {
      "date": "2026-06-17",
      "pick": "PIT",
      "game": "PIT @ OAK",
      "odds": -114,
      "edge": 0.061,
      "result": "W",
      "pnl_u": 0.88
    },
    {
      "date": "2026-06-19",
      "pick": "WSH",
      "game": "WSH @ TB",
      "odds": 115,
      "edge": 0.062,
      "result": "L",
      "pnl_u": -1.0
    },
    {
      "date": "2026-06-20",
      "pick": "WSH",
      "game": "WSH @ TB",
      "odds": 115,
      "edge": 0.068,
      "result": "W",
      "pnl_u": 1.15
    },
    {
      "date": "2026-06-20",
      "pick": "LAA",
      "game": "LAA @ OAK",
      "odds": 154,
      "edge": 0.061,
      "result": "W",
      "pnl_u": 1.54
    },
    {
      "date": "2026-06-21",
      "pick": "LAA",
      "game": "LAA @ OAK",
      "odds": 117,
      "edge": 0.074,
      "result": "W",
      "pnl_u": 1.17
    },
    {
      "date": "2026-06-22",
      "pick": "MIN",
      "game": "LAD @ MIN",
      "odds": 136,
      "edge": 0.075,
      "result": "L",
      "pnl_u": -1.0
    },
    {
      "date": "2026-06-22",
      "pick": "LAA",
      "game": "BAL @ LAA",
      "odds": 147,
      "edge": 0.066,
      "result": "L",
      "pnl_u": -1.0
    },
    {
      "date": "2026-06-23",
      "pick": "MIL",
      "game": "MIL @ CIN",
      "odds": -101,
      "edge": 0.073,
      "result": "W",
      "pnl_u": 0.99
    },
    {
      "date": "2026-06-23",
      "pick": "MIN",
      "game": "LAD @ MIN",
      "odds": 160,
      "edge": 0.063,
      "result": "L",
      "pnl_u": -1.0
    },
    {
      "date": "2026-06-23",
      "pick": "STL",
      "game": "ARI @ STL",
      "odds": -104,
      "edge": 0.069,
      "result": "L",
      "pnl_u": -1.0
    },
    {
      "date": "2026-06-24",
      "pick": "PIT",
      "game": "SEA @ PIT",
      "odds": -109,
      "edge": 0.061,
      "result": "W",
      "pnl_u": 0.92
    },
    {
      "date": "2026-06-24",
      "pick": "KC",
      "game": "KC @ TB",
      "odds": 136,
      "edge": 0.061,
      "result": "L",
      "pnl_u": -1.0
    }
  ],
  "last30": {
    "wins": 18,
    "losses": 12,
    "units": 9.33
  },
  "avg_clv": 0.0028,
  "clv_count": 457,
  "clv_positive_pct": 0.47
}